packmol_memgen/__init__.py
packmol_memgen/__version__.py
packmol_memgen/main.py
packmol_memgen/data/LICENSE.Apache-2.0
packmol_memgen/data/extra_solvents.lib
packmol_memgen/data/frcmod.lipid_ext
packmol_memgen/data/frcmod.solvents
packmol_memgen/data/insane_lipids.txt
packmol_memgen/data/insane_solvents.txt
packmol_memgen/data/leaprc.extra_solvents
packmol_memgen/data/leaprc.lipid_ext
packmol_memgen/data/lipid_ext.lib
packmol_memgen/data/martini_v3.0.0.itp
packmol_memgen/data/memgen.parm
packmol_memgen/data/pdbs.tar.gz
packmol_memgen/data/solvent.parm
packmol_memgen/example/example.sh
packmol_memgen/lib/__init__.py
packmol_memgen/lib/amber.py
packmol_memgen/lib/utils.py
packmol_memgen/lib/charmmlipid2amber/__init__.py
packmol_memgen/lib/charmmlipid2amber/charmmlipid2amber.csv
packmol_memgen/lib/charmmlipid2amber/charmmlipid2amber.py
packmol_memgen/lib/pdbremix/LICENSE
packmol_memgen/lib/pdbremix/__init__.py
packmol_memgen/lib/pdbremix/_version.py
packmol_memgen/lib/pdbremix/amber.py
packmol_memgen/lib/pdbremix/asa.py
packmol_memgen/lib/pdbremix/data.py
packmol_memgen/lib/pdbremix/fetch.py
packmol_memgen/lib/pdbremix/force.py
packmol_memgen/lib/pdbremix/gromacs.py
packmol_memgen/lib/pdbremix/namd.py
packmol_memgen/lib/pdbremix/pdbatoms.py
packmol_memgen/lib/pdbremix/pdbtext.py
packmol_memgen/lib/pdbremix/protein.py
packmol_memgen/lib/pdbremix/pymol.py
packmol_memgen/lib/pdbremix/rmsd.py
packmol_memgen/lib/pdbremix/simulate.py
packmol_memgen/lib/pdbremix/spacehash.py
packmol_memgen/lib/pdbremix/trajectory.py
packmol_memgen/lib/pdbremix/util.py
packmol_memgen/lib/pdbremix/v3.py
packmol_memgen/lib/pdbremix/v3array.py
packmol_memgen/lib/pdbremix/v3numpy.py
packmol_memgen/lib/pdbremix/volume.py
packmol_memgen/lib/pdbremix/data/aminoacid.pdb
packmol_memgen/lib/pdbremix/data/binaries.json
packmol_memgen/lib/pdbremix/data/charmm22.parameter
packmol_memgen/lib/pdbremix/data/charmm22.topology
packmol_memgen/lib/pdbremix/data/color_b.py
packmol_memgen/lib/pdbremix/data/hin.lib
packmol_memgen_minimal-1.1.17.dist-info/METADATA
packmol_memgen_minimal-1.1.17.dist-info/WHEEL
packmol_memgen_minimal-1.1.17.dist-info/entry_points.txt
packmol_memgen_minimal-1.1.17.dist-info/licenses/LICENSE
packmol_memgen_minimal-1.1.17.dist-info/RECORD
