Metadata-Version: 2.4
Name: packmol-memgen-minimal
Version: 1.1.17
Summary: A fork of packmol_memgen from AmberTools, a PACKMOL wrapper for packing proteins into membranes, aimed to be minimal, mordernized and self-contained.
Project-URL: Homepage, https://github.com/xiaoxuan-yu/packmol_memgen_minimal/
Author-email: Xiaoxuan Yu <xiaoxuan_yu@pku.edu.cn>
License:  GNU GENERAL PUBLIC LICENSE
License-File: LICENSE
Classifier: Development Status :: 3 - Alpha
Classifier: Intended Audience :: Science/Research
Classifier: License :: OSI Approved :: GNU General Public License v2 (GPLv2)
Classifier: Programming Language :: Python
Classifier: Programming Language :: Python :: 3
Classifier: Topic :: Scientific/Engineering
Classifier: Topic :: Scientific/Engineering :: Bio-Informatics
Classifier: Topic :: Scientific/Engineering :: Chemistry
Requires-Python: >=3.11
Requires-Dist: hatch-vcs>=0.5.0
Requires-Dist: matplotlib
Requires-Dist: numpy
Requires-Dist: pandas
Requires-Dist: pdb2pqr>=3.7.1
Requires-Dist: scipy
Requires-Dist: tqdm
Provides-Extra: full
Requires-Dist: mdtraj; extra == 'full'
Requires-Dist: mempro; extra == 'full'
Requires-Dist: packmol==21.1.4; extra == 'full'
Requires-Dist: vermouth; extra == 'full'
Provides-Extra: martini
Requires-Dist: mdtraj; extra == 'martini'
Requires-Dist: vermouth; extra == 'martini'
Provides-Extra: mempro
Requires-Dist: mempro; extra == 'mempro'
Provides-Extra: packmol
Requires-Dist: packmol==21.1.14; extra == 'packmol'
